Metadata-Version: 2.4
Name: cjm-text-plugin-system
Version: 0.0.1
Summary: Defines standardized interfaces and data structures for text processing plugins, enabling modular NLP operations like sentence splitting, tokenization, and chunking within the cjm-plugin-system ecosystem.
Home-page: https://github.com/cj-mills/cjm-text-plugin-system
Author: Christian J. Mills
Author-email: 9126128+cj-mills@users.noreply.github.com
License: Apache-2.0
Keywords: nbdev jupyter notebook python
Classifier: Development Status :: 4 - Beta
Classifier: Intended Audience :: Developers
Classifier: Natural Language :: English
Classifier: Programming Language :: Python :: 3.11
Classifier: Programming Language :: Python :: 3.12
Classifier: Programming Language :: Python :: 3.13
Requires-Python: >=3.11
License-File: LICENSE
Requires-Dist: cjm_plugin_system
Provides-Extra: dev
Dynamic: author
Dynamic: author-email
Dynamic: classifier
Dynamic: description
Dynamic: description-content-type
Dynamic: home-page
Dynamic: keywords
Dynamic: license
Dynamic: license-file
Dynamic: provides-extra
Dynamic: requires-dist
Dynamic: requires-python
Dynamic: summary
